Metadata-Version: 2.1
Name: aprillang
Version: 1.0.0
Summary: Programming Language to make API [Utilise the power of all languages in you API]
Home-page: https://github.com/merwin-asm/April
Author: Cactochan
License: UNKNOWN
Keywords: API,programming,language,april,aprillang
Platform: any
Classifier: Programming Language :: Python :: 3
Requires-Python: >=3.8
License-File: LICENSE
